moonraker-0.10.0.dist-info/METADATA
moonraker-0.10.0.dist-info/WHEEL
moonraker-0.10.0.dist-info/entry_points.txt
moonraker-0.10.0.dist-info/licenses/LICENSE
moonraker/__init__.py
moonraker/__main__.py
moonraker/__version__.py
moonraker/assets/__init__.py
moonraker/assets/default_allowed_services
moonraker/assets/welcome.html
moonraker/common.py
moonraker/components/__init__.py
moonraker/components/analysis.py
moonraker/components/announcements.py
moonraker/components/application.py
moonraker/components/authorization.py
moonraker/components/button.py
moonraker/components/data_store.py
moonraker/components/database.py
moonraker/components/dbus_manager.py
moonraker/components/extensions.py
moonraker/components/file_manager/__init__.py
moonraker/components/file_manager/file_manager.py
moonraker/components/file_manager/metadata.py
moonraker/components/gpio.py
moonraker/components/history.py
moonraker/components/http_client.py
moonraker/components/job_queue.py
moonraker/components/job_state.py
moonraker/components/klippy_apis.py
moonraker/components/klippy_connection.py
moonraker/components/ldap.py
moonraker/components/machine.py
moonraker/components/mqtt.py
moonraker/components/notifier.py
moonraker/components/octoprint_compat.py
moonraker/components/paneldue.py
moonraker/components/power.py
moonraker/components/proc_stats.py
moonraker/components/secrets.py
moonraker/components/sensor.py
moonraker/components/shell_command.py
moonraker/components/simplyprint.py
moonraker/components/spoolman.py
moonraker/components/td1.py
moonraker/components/template.py
moonraker/components/update_manager/__init__.py
moonraker/components/update_manager/app_deploy.py
moonraker/components/update_manager/base_deploy.py
moonraker/components/update_manager/common.py
moonraker/components/update_manager/git_deploy.py
moonraker/components/update_manager/net_deploy.py
moonraker/components/update_manager/python_deploy.py
moonraker/components/update_manager/system_deploy.py
moonraker/components/update_manager/update_manager.py
moonraker/components/webcam.py
moonraker/components/websockets.py
moonraker/components/wled.py
moonraker/components/zeroconf.py
moonraker-0.10.0.dist-info/RECORD
