Metadata-Version: 2.1
Name: moonraker
Version: 0.10.0
Summary: API Server for Klipper
Keywords: klipper,3D printing,server,moonraker
Author-Email: Eric Callahan <arksine.code@gmail.com>
License: GPL-3.0-only
Classifier: Development Status :: 4 - Beta
Classifier: Topic :: Internet :: WWW/HTTP :: HTTP Servers
Classifier: Programming Language :: Python :: 3
Classifier: Programming Language :: Python :: 3.7
Classifier: Programming Language :: Python :: 3.8
Classifier: Programming Language :: Python :: 3.9
Classifier: Programming Language :: Python :: 3.10
Classifier: Programming Language :: Python :: 3.11
Classifier: Programming Language :: Python :: 3.12
Classifier: Programming Language :: Python :: 3.13
Classifier: Programming Language :: Python :: 3.14
Project-URL: homepage, https://github.com/Arksine/moonraker
Project-URL: repository, https://github.com/Arksine/moonraker
Project-URL: documentation, https://moonraker.readthedocs.io
Project-URL: changelog, https://moonraker.readthedocs.io/en/latest/changelog/
Requires-Python: >=3.7
Requires-Dist: tornado<=6.5.4,>=6.2.0
Requires-Dist: pyserial==3.4
Requires-Dist: pillow<=12.1.0,>=9.5.0
Requires-Dist: streaming-form-data<=1.19.1,>=1.11.0
Requires-Dist: distro==1.9.0
Requires-Dist: inotify-simple==2.0.1
Requires-Dist: libnacl==2.1.0
Requires-Dist: paho-mqtt==2.1.0
Requires-Dist: zeroconf<=0.148.0,>=0.131.0
Requires-Dist: preprocess-cancellation==0.2.1
Requires-Dist: jinja2==3.1.6
Requires-Dist: dbus-fast<=3.1.2,>=2.21.3
Requires-Dist: apprise<=1.9.6,>=1.9.3
Requires-Dist: ldap3==2.9.1
Requires-Dist: python-periphery==2.4.1
Requires-Dist: importlib_metadata<=8.7.1,>=6.7.0
Provides-Extra: msgspec
Requires-Dist: msgspec>=0.18.4; python_version >= "3.8" and extra == "msgspec"
Provides-Extra: uvloop
Requires-Dist: uvloop>=0.17.0; extra == "uvloop"
Provides-Extra: speedups
Requires-Dist: msgspec>=0.18.4; python_version >= "3.8" and extra == "speedups"
Requires-Dist: uvloop>=0.17.0; extra == "speedups"
Provides-Extra: dev
Requires-Dist: pre-commit; extra == "dev"
Requires-Dist: build; extra == "dev"
Requires-Dist: mypy; extra == "dev"
Requires-Dist: ruff; extra == "dev"
Requires-Dist: twine; extra == "dev"
